opencapif_sdk/__init__.py
opencapif_sdk/api_schema_translator.py
opencapif_sdk/capif_event_feature.py
opencapif_sdk/capif_invoker_connector.py
opencapif_sdk/capif_logging_feature.py
opencapif_sdk/capif_provider_connector.py
opencapif_sdk/service_discoverer.py
opencapif_sdk-0.1.21.dist-info/licenses/LICENSE
opencapif_sdk-0.1.21.dist-info/METADATA
opencapif_sdk-0.1.21.dist-info/WHEEL
opencapif_sdk-0.1.21.dist-info/top_level.txt
opencapif_sdk-0.1.21.dist-info/RECORD
