Metadata-Version: 2.4
Name: opencapif_sdk
Version: 0.1.21
Summary: This repository develops a Python Software Development Kit(SDK) which focuses on connecting to OpenCAPIF (Common API Framework for 3GPP Northbound APIs) in a simple way, lowering integration complexity and allowing developers to focus on Network Applications (Network Apps) or services development.
Home-page: https://github.com/Telefonica/pesp_capif_sdk
Author: JorgeEcheva, dgs-cgm
Author-email: jorge.echevarriauribarri.practicas@telefonica.com, daniel.garciasanchez@telefonica.com
License: LICENSE
Keywords: pesp_capif_sdk,capif,sdk capif,opencapif_sdk
Classifier: Programming Language :: Python :: 3
Classifier: Operating System :: OS Independent
Requires-Python: >=3.9
License-File: LICENSE
Requires-Dist: requests==2.32.3
Requires-Dist: PyYAML==6.0.1
Requires-Dist: cryptography==38.0.4
Requires-Dist: pyOpenSSL==22.1.0
Requires-Dist: urllib3==2.2.2
Requires-Dist: certifi==2024.7.4
Requires-Dist: idna==3.7
Requires-Dist: Flask==3.0.3
Requires-Dist: Flask-JWT-Extended==4.6.0
Requires-Dist: Jinja2==3.1.4
Requires-Dist: MarkupSafe==2.1.5
Requires-Dist: six==1.16.0
Requires-Dist: typing-extensions>=4.8.0
Requires-Dist: Werkzeug==3.0.4
Requires-Dist: pytest==8.3.2
Requires-Dist: flake8==3.9.2
Requires-Dist: coverage==4.5.4
Requires-Dist: mccabe==0.6.1
Requires-Dist: pycodestyle==2.7.0
Requires-Dist: pyflakes==2.3.1
Requires-Dist: python-dateutil==2.9.0.post0
Requires-Dist: jinja2-time==0.2.0
Requires-Dist: text-unidecode==1.3
Requires-Dist: binaryornot==0.4.4
Dynamic: author
Dynamic: author-email
Dynamic: classifier
Dynamic: description
Dynamic: description-content-type
Dynamic: home-page
Dynamic: keywords
Dynamic: license
Dynamic: license-file
Dynamic: requires-dist
Dynamic: requires-python
Dynamic: summary
